predacons_cli/__init__.py
predacons_cli/src/__init__.py
predacons_cli/src/cli.py
predacons_cli/src/predacons_cli.py
predacons_cli/src/rag.py
predacons_cli-0.0.101.dist-info/LICENSE
predacons_cli-0.0.101.dist-info/METADATA
predacons_cli-0.0.101.dist-info/WHEEL
predacons_cli-0.0.101.dist-info/entry_points.txt
predacons_cli-0.0.101.dist-info/top_level.txt
predacons_cli-0.0.101.dist-info/RECORD
