Metadata-Version: 2.1
Name: predacons_cli
Version: 0.0.101
Summary: comand line interface for Predacons
Home-page: https://github.com/shouryashashank/predacons-gui
Author: shouryashashank
Author-email: shouryashashank@gmail.com
License: MIT
Classifier: License :: OSI Approved :: MIT License
Classifier: Programming Language :: Python :: 3.10
Classifier: Operating System :: OS Independent
Requires-Python: >=3.10
License-File: LICENSE
Requires-Dist: predacons >=0.0.126
Requires-Dist: rich >=13.7.1
Requires-Dist: langchain-community >=0.3.2
Requires-Dist: langchain >=0.3.3
Requires-Dist: requests >=2.32.3
Requires-Dist: beautifulsoup4 >=4.12.3
Requires-Dist: googlesearch-python >=1.2.5
Provides-Extra: dev
Requires-Dist: pytest >=7.0 ; extra == 'dev'
Requires-Dist: twine >=4.0.2 ; extra == 'dev'
